{
  "http://schemas.xmlsoap.org/soap/envelope/:Envelope": {
    "http://schemas.xmlsoap.org/soap/envelope/:Header": null,
    "http://schemas.xmlsoap.org/soap/envelope/:Body": {
      "x:VertexEnvelope": {
        "x:Login": {
          "x:TrustedId": "8105174526942882"
        },
        "x:QuotationRequest": {
          "@documentDate": "2021-02-09",
          "@documentNumber": "W01005739594790",
          "@transactionType": "SALE",
          "@xmlns": {
            "SOAP-ENV": "http://schemas.xmlsoap.org/soap/envelope/",
            "ns2": "urn:vertexinc:o-series:tps:7:0"
          },
          "x:LineItem": [
            {
              "@lineItemId": "243781821_ITM",
              "@lineItemNumber": "243781821",
              "x:Seller": {
                "x:Company": "10",
                "x:PhysicalOrigin": {
                  "@taxAreaId": "330590000"
                }
              },
              "x:Customer": {
                "@isTaxExempt": "false",
                "x:Destination": {
                  "x:StreetAddress1": "17 Peace Street",
                  "x:City": "Stratford",
                  "x:MainDivision": "CT",
                  "x:PostalCode": "06615",
                  "x:Country": "USA"
                }
              },
              "x:Product": {
                "@productClass": "03",
                "#text": "145324SRDV4"
              },
              "x:Quantity": "1.0",
              "x:ExtendedPrice": "50.24",
              "x:FlexibleFields": {
                "x:FlexibleCodeField": [
                  {
                    "@fieldId": "1",
                    "#text": "Original"
                  },
                  {
                    "@fieldId": "2",
                    "#text": "WEB"
                  },
                  {
                    "@fieldId": "8",
                    "#text": "145324SRDV4"
                  },
                  {
                    "@fieldId": "9",
                    "#text": "1001"
                  },
                  {
                    "@fieldId": "11",
                    "#text": "GPT"
                  },
                  {
                    "@fieldId": "15",
                    "#text": "CT"
                  },
                  {
                    "@fieldId": "20",
                    "#text": "raiza arroyo"
                  },
                  {
                    "@fieldId": "21"
                  },
                  {
                    "@fieldId": "22",
                    "#text": "Stratford"
                  },
                  {
                    "@fieldId": "23",
                    "#text": "CT"
                  },
                  {
                    "@fieldId": "3",
                    "#text": "03"
                  }
                ],
                "x:FlexibleNumericField": {
                  "@fieldId": "3",
                  "#text": "1.0"
                }
              }
            },
            {
              "@lineItemId": "243781821_FRT",
              "@lineItemNumber": "243781821",
              "x:Seller": {
                "x:Company": "10",
                "x:PhysicalOrigin": {
                  "@taxAreaId": "330590000"
                }
              },
              "x:Customer": {
                "@isTaxExempt": "false",
                "x:Destination": {
                  "x:StreetAddress1": "17 Peace Street",
                  "x:City": "Stratford",
                  "x:MainDivision": "CT",
                  "x:PostalCode": "06615",
                  "x:Country": "USA"
                }
              },
              "x:Product": {
                "@productClass": "03",
                "#text": "FRT"
              },
              "x:ExtendedPrice": "17.98",
              "x:FlexibleFields": {
                "x:FlexibleCodeField": [
                  {
                    "@fieldId": "1",
                    "#text": "Original"
                  },
                  {
                    "@fieldId": "2",
                    "#text": "WEB"
                  },
                  {
                    "@fieldId": "8",
                    "#text": "145324SRDV4"
                  },
                  {
                    "@fieldId": "9",
                    "#text": "1001"
                  },
                  {
                    "@fieldId": "11",
                    "#text": "GPT"
                  },
                  {
                    "@fieldId": "15",
                    "#text": "CT"
                  },
                  {
                    "@fieldId": "20",
                    "#text": "raiza arroyo"
                  },
                  {
                    "@fieldId": "21"
                  },
                  {
                    "@fieldId": "22",
                    "#text": "Stratford"
                  },
                  {
                    "@fieldId": "23",
                    "#text": "CT"
                  },
                  {
                    "@fieldId": "3",
                    "#text": "03"
                  }
                ],
                "x:FlexibleNumericField": {
                  "@fieldId": "3",
                  "#text": "1.0"
                }
              }
            }
          ]
        }
      }
    }
  }
}